{
  "brand": {
    "name": "WM GROUP",
    "logo": "/assets/uploads/logo.png"
  },
  "partner": {
    "title": {
      "en": "Partner with us",
      "ar": ""
    },
    "desc": {
      "en": "You can reach us here:",
      "ar": ""
    },
    "image": "/assets/uploads/picture-14.jpg",
    "contact": {
      "address": {
        "en": "Damascus, Syria — Your Address Here",
        "ar": ""
      },
      "phoneLabel": {
        "en": "Phone",
        "ar": ""
      },
      "phoneE164": "+963000000000",
      "whatsappLabel": {
        "en": "WhatsApp",
        "ar": ""
      },
      "whatsappNumberE164": "+963000000000",
      "instagramLabel": {
        "en": "Instagram",
        "ar": ""
      },
      "instagramName": "wmgroup",
      "instagramUrl": "https://instagram.com/wmgroup"
    }
  },
  "about": {
    "p1": "Map { \"en\": \"Waleed Medaa Group is a Syrian architectural firm based in Damascus, delivering comprehensive architectural and construction solutions for high-end projects.\\n\\nThe firm specializes in construction management and supervision, providing end-to-end services from concept through execution. With multidisciplinary design and management teams across all engineering fields, Waleed Medaa Group ensures full project coordination, technical excellence, and execution precision.\", \"ar\": \"مجموعة وليد مدى هي شركة معمارية سورية مقرها دمشق، تقدم حلولًا متكاملة في الهندسة المعمارية والبناء للمشاريع الراقية.\\n\\nتتخصص الشركة في إدارة المشاريع والإشراف على التنفيذ، وتوفر خدمات شاملة تبدأ من مرحلة الفكرة وحتى مرحلة التنفيذ. وبفضل فرق التصميم والإدارة متعددة التخصصات التي تضم مختلف المجالات الهندسية، تضمن مجموعة وليد مدى تنسيقًا كاملًا للمشاريع، وتميزًا تقنيًا، ودقة عالية في التنفيذ.\" }\n",
    "p2": {
      "en": "Our work spans residential housing, commercial real estate, logistics centers, leisure developments, and high-rise buildings. Every project is approached with a commitment to quality, functionality, and architectural integrity, with the ultimate goal of meeting—and surpassing—client expectations.",
      "ar": ""
    }
  },
  "gallery": [
    {
      "image": "/assets/uploads/picture-9.jpg"
    },
    {
      "image": "/assets/uploads/picture-10.jpg"
    },
    {
      "image": "/assets/uploads/picture-11.jpg"
    },
    {
      "image": "/assets/uploads/picture-12.jpg"
    },
    {
      "image": "/assets/uploads/picture-13.jpg"
    }
  ],
  "langDefault": "en",
  "projects": [
    {
      "side": "right",
      "title": {
        "en": "Villa concept in Yaffour",
        "ar": ""
      },
      "meta": {
        "en": "Syria • Residential • Yaffour",
        "ar": ""
      },
      "desc": {
        "en": "This is a conceptual architectural rendering of a luxury villa planned for Yaafour, showcasing a neoclassical design with formal symmetry, landscaped grounds, and gated access.",
        "ar": ""
      },
      "image": "/assets/uploads/picture-7.jpg"
    },
    {
      "side": "left",
      "title": {
        "en": "Marota City",
        "ar": ""
      },
      "meta": {
        "en": "Syria • Residential • Block H10",
        "ar": ""
      },
      "desc": {
        "en": "A conceptual residential development in Marota City, showcasing a contemporary architectural design intended to support modern urban living.",
        "ar": ""
      },
      "image": "/assets/uploads/picture-8.jpg"
    }
  ],
  "hero": {
    "word": "Map { \"en\": \"\", \"ar\": \"\" }",
    "image": "/assets/uploads/picture-1.jpg"
  },
  "footer": {
    "email": "WMGROUP@gmail.com"
  },
  "services": [
    {
      "num": "01",
      "title": {
        "en": "Architecture",
        "ar": ""
      },
      "text": {
        "en": "We design buildings that are purposeful, enduring, and deeply connected to their surroundings. Our architectural services combine creativity with technical rigor to deliver clear, buildable solutions.",
        "ar": ""
      },
      "bullets": [
        {
          "bullet": {
            "en": "Concept Design",
            "ar": ""
          }
        },
        {
          "bullet": {
            "en": "Architectural Planning",
            "ar": ""
          }
        },
        {
          "bullet": {
            "en": "3D Visualization & Modeling",
            "ar": ""
          }
        },
        {
          "bullet": {
            "en": "Construction Documentation",
            "ar": ""
          }
        }
      ],
      "image": "/assets/uploads/picture-3.jpg"
    },
    {
      "num": "02",
      "title": {
        "en": "Interior Design",
        "ar": ""
      },
      "text": {
        "en": "We create refined interior environments that balance aesthetics, functionality, and material quality. Our interior design approach ensures cohesive spaces that enhance user experience and complement the architectural vision.",
        "ar": ""
      },
      "bullets": [
        {
          "bullet": {
            "en": "Space Planning & Layout Design",
            "ar": ""
          }
        },
        {
          "bullet": {
            "en": "Material & Finishes Selection",
            "ar": ""
          }
        },
        {
          "bullet": {
            "en": "Custom Furniture & Joinery Design",
            "ar": ""
          }
        },
        {
          "bullet": {
            "en": "Lighting & Interior Visualization",
            "ar": ""
          }
        }
      ],
      "image": "/assets/uploads/picture-4.jpg"
    },
    {
      "num": "03",
      "title": {
        "en": "Layout Planning",
        "ar": ""
      },
      "text": {
        "en": "We develop efficient layout solutions that optimize circulation, usability, and spatial clarity. Each plan is carefully structured to support functionality, flexibility, and long-term performance.",
        "ar": ""
      },
      "bullets": [
        {
          "bullet": {
            "en": "Spatial Zoning & Circulation Studies",
            "ar": ""
          }
        },
        {
          "bullet": {
            "en": "Functional Area Planning",
            "ar": ""
          }
        },
        {
          "bullet": {
            "en": "Residential & Commercial Layouts",
            "ar": ""
          }
        },
        {
          "bullet": {
            "en": "Optimization for Code & Efficiency",
            "ar": ""
          }
        }
      ],
      "image": "/assets/uploads/picture-5.jpg"
    },
    {
      "num": "04",
      "title": {
        "en": "Project Management",
        "ar": ""
      },
      "text": {
        "en": "We provide comprehensive project management and construction supervision services to ensure projects are delivered on time, within budget, and to the highest quality standards.",
        "ar": ""
      },
      "bullets": [
        {
          "bullet": {
            "en": "Construction Management & Supervision",
            "ar": ""
          }
        },
        {
          "bullet": {
            "en": "Cost Control & Scheduling",
            "ar": ""
          }
        },
        {
          "bullet": {
            "en": "Multidisciplinary Coordination",
            "ar": ""
          }
        },
        {
          "bullet": {
            "en": "Quality Assurance & Site Follow-up",
            "ar": ""
          }
        }
      ],
      "image": "/assets/uploads/picture-6.jpg"
    }
  ]
}
